{
	"objectCount":	16,
	"objects":	[{
			"nametag":	"hf base",
			"pos":	[77.3419418334961, 0, 98.671600341796875],
			"rot":	[0, 0, 0, 1],
			"scale":	[256, 24, 256],
			"objectType":	"Heightfield",
			"pipeline":	"Heightfield",
			"heightfieldData":	{
				"pathToHeightmap":	"assets/heightmaps/clouds.dds",
				"width":	256
			}
		}, {
			"nametag":	"lighthouse",
			"pos":	[170.51612854003906, 38.045482635498047, 175.34268188476562],
			"rot":	[0, 0, 0, 1],
			"scale":	[12, 32, 12],
			"objectType":	"Primitive",
			"pipeline":	"Default",
			"primitiveData":	{
				"primitiveType":	"Cylinder"
			}
		}, {
			"nametag":	"bridge",
			"pos":	[84.450325012207031, 10.186640739440918, 31.962961196899414],
			"rot":	[0, 0.23690134286880493, 0, 0.971533715724945],
			"scale":	[8.3526782989501953, 1, 37.426109313964844],
			"objectType":	"Primitive",
			"pipeline":	"Default",
			"primitiveData":	{
				"primitiveType":	"Cube"
			}
		}, {
			"nametag":	"pont",
			"pos":	[48.504432678222656, 7.5241203308105469, 110.23626708984375],
			"rot":	[0, -0.643200933933258, 0, 0.765697419643402],
			"scale":	[2.9999988079071045, 0.10000000149011612, 10.000000953674316],
			"objectType":	"Primitive",
			"pipeline":	"Default",
			"primitiveData":	{
				"primitiveType":	"Cube"
			}
		}, {
			"nametag":	"wall1",
			"pos":	[0, 24.314275741577148, 6.9976873397827148],
			"rot":	[0, 0, 0, 1],
			"scale":	[3, 3.5, 0.33000001311302185],
			"objectType":	"Primitive",
			"pipeline":	"Default",
			"primitiveData":	{
				"primitiveType":	"Cube"
			}
		}, {
			"nametag":	"wall bottom of window",
			"pos":	[2.4677901268005371, 25.5545539855957, 7],
			"rot":	[0, 0, 0, 1],
			"scale":	[2, 1, 0.33000001311302185],
			"objectType":	"Primitive",
			"pipeline":	"Default",
			"primitiveData":	{
				"primitiveType":	"Cube"
			}
		}, {
			"nametag":	"(copy)",
			"pos":	[6.3464055061340332, 24.314275741577148, 4.51845407485962],
			"rot":	[0, 0.70686262845993042, 0, 0.70735085010528564],
			"scale":	[4.8386588096618652, 3.4999997615814209, 0.33000123500823975],
			"objectType":	"Primitive",
			"pipeline":	"Default",
			"primitiveData":	{
				"primitiveType":	"Cube"
			}
		}, {
			"nametag":	"(copy)",
			"pos":	[2.4677901268005371, 23.065645217895508, 7],
			"rot":	[0, 0, 0, 1],
			"scale":	[2, 1, 0.33000001311302185],
			"objectType":	"Primitive",
			"pipeline":	"Default",
			"primitiveData":	{
				"primitiveType":	"Cube"
			}
		}, {
			"nametag":	"(copy)",
			"pos":	[2.5078935623168945, 26.024778366088867, 4.67046594619751],
			"rot":	[0, 0, 0, 1],
			"scale":	[8, 0.20000000298023224, 5],
			"objectType":	"Primitive",
			"pipeline":	"Default",
			"primitiveData":	{
				"primitiveType":	"Cube"
			}
		}, {
			"nametag":	"(copy)",
			"pos":	[2.31182050704956, 24.314275741577148, 2.3357553482055664],
			"rot":	[0, 0, 0, 1],
			"scale":	[7.6292014122009277, 3.5, 0.33000001311302185],
			"objectType":	"Primitive",
			"pipeline":	"Default",
			"primitiveData":	{
				"primitiveType":	"Cube"
			}
		}, {
			"nametag":	"(copy)",
			"pos":	[4.9153933525085449, 24.314275741577148, 6.9976873397827148],
			"rot":	[0, 0, 0, 1],
			"scale":	[3, 3.5, 0.33000001311302185],
			"objectType":	"Primitive",
			"pipeline":	"Default",
			"primitiveData":	{
				"primitiveType":	"Cube"
			}
		}, {
			"nametag":	"(copy)",
			"pos":	[-0.700023651123047, 21.465200424194336, 2.5326395034790039],
			"rot":	[0, 0, -0.27480900287628174, 0.96149879693985],
			"scale":	[2.54563045501709, 1, 5.1175422668457031],
			"objectType":	"Primitive",
			"pipeline":	"Default",
			"primitiveData":	{
				"primitiveType":	"Cube"
			}
		}, {
			"nametag":	"(copy)",
			"pos":	[2.5078935623168945, 22.095653533935547, 4.67046594619751],
			"rot":	[0, 0, 0, 1],
			"scale":	[8, 1, 5],
			"objectType":	"Primitive",
			"pipeline":	"Default",
			"primitiveData":	{
				"primitiveType":	"Cube"
			}
		}, {
			"nametag":	"(copy)",
			"pos":	[-3.1580913066864014, 22.095653533935547, 2.3264524936676025],
			"rot":	[0, 0, 0, 1],
			"scale":	[3.3257861137390137, 1, 5.1175422668457031],
			"objectType":	"Primitive",
			"pipeline":	"Default",
			"primitiveData":	{
				"primitiveType":	"Cube"
			}
		}, {
			"nametag":	"blah",
			"pos":	[-0.700023651123047, 21.649660110473633, -0.13908934593200684],
			"rot":	[0, 0, 0, 1],
			"scale":	[2.54563045501709, 3.5413668155670166, 0.20000000298023224],
			"objectType":	"Primitive",
			"pipeline":	"Default",
			"primitiveData":	{
				"primitiveType":	"Cube"
			}
		}, {
			"nametag":	"blah",
			"pos":	[-3.2331006526947021, 23.744104385375977, 4.8754105567932129],
			"rot":	[0, 0, 0, 1],
			"scale":	[3.5259807109832764, 3.5413668155670166, 0.20000000298023224],
			"objectType":	"Primitive",
			"pipeline":	"Default",
			"primitiveData":	{
				"primitiveType":	"Cube"
			}
		}]
}